setup.py
caching_s3_proxy.egg-info/PKG-INFO
caching_s3_proxy.egg-info/SOURCES.txt
caching_s3_proxy.egg-info/dependency_links.txt
caching_s3_proxy.egg-info/entry_points.txt
caching_s3_proxy.egg-info/not-zip-safe
caching_s3_proxy.egg-info/requires.txt
caching_s3_proxy.egg-info/top_level.txt
proxy/__init__.py
proxy/cache.py
proxy/run.py
proxy/test_cache.py
proxy/wsgi.py