Metadata-Version: 1.1
Name: caching-s3-proxy
Version: 0.7
Summary: provides an unauthenticated plain HTTP frontend for public and private S3 buckets, and caches on the filesystem using an LRU cache
Home-page: https://github.com/rhelmer/caching-s3-proxy
Author: Rob Helmer
Author-email: rhelmer@rhelmer.org
License: MPL
Keywords: caching,lru,s3,proxy,unauthenticated
Platform: UNKNOWN
Classifier: Intended Audience :: Developers
Classifier: Intended Audience :: System Administrators
Classifier: License :: OSI Approved :: Mozilla Public License 1.1 (MPL 1.1)
Classifier: Programming Language :: Python :: 2.7
Classifier: Topic :: Internet :: WWW/HTTP :: WSGI :: Application
